rotki_releases-2.0.1.dist-info/metadata.json
rotki_releases-2.0.1.dist-info/top_level.txt
rotki_releases-2.0.1.dist-info/RECORD
rotki_releases-2.0.1.dist-info/METADATA
rotki_releases-2.0.1.dist-info/DESCRIPTION.rst
rotki_releases-2.0.1.dist-info/WHEEL
releases/models.py
releases/__init__.py
releases/util.py
releases/_version.py
releases/line_manager.py
